<?xml version='1.0' encoding='utf-8'?>
<vax>
    <table>
        <name>USERINFO</name>
        <hook>./usertroller</hook>
        <axios>
            <method>POST</method>
            <baseURL>http://www.server.com</baseURL>
            <url>/api/user</url>
            <withCredentials>true</withCredentials>
            <headers>
                <Content-Type>application/x-www-form-urlencoded</Content-Type>
            </headers>
        </axios>
        <cache>
            <time>3</time>
        </cache>
        <vuex>    
        </vuex>     
    </table>    
    <table>
        <name>MEMBERINFO</name>
        <hook>./membertroller</hook>
        <axios>
            <method>POST</method>
            <baseURL>http://www.server.com</baseURL>
            <url>/api/member</url>
            <withCredentials>true</withCredentials>
            <headers>
                <Content-Type>application/x-www-form-urlencoded</Content-Type>
            </headers>
        </axios>
        <vuex>    
        </vuex>     
    </table>
</vax>
